tapmap/__init__.py
tapmap/char_map.py
tapmap/processing.py
tapmap/images/keyboard.png
tapmap-1.4.dist-info/METADATA
tapmap-1.4.dist-info/RECORD
tapmap-1.4.dist-info/WHEEL
tapmap-1.4.dist-info/entry_points.txt
tapmap-1.4.dist-info/top_level.txt
