Metadata-Version: 2.1
Name: tapmap
Version: 1.4
Summary: A generator for keyboard heatmap images
Home-page: https://github.com/AnonGuy/TapMap
Author: Jeremiah Boby
Author-email: jeremiahboby@gmail.com
License: UNKNOWN
Keywords: matplotlib PIL numpy
Platform: UNKNOWN
Classifier: Programming Language :: Python :: 3
Requires-Dist: Pillow
Requires-Dist: numpy
Requires-Dist: matplotlib
